Workbook
Name averageofclothing: Sheet1!$R$18
Name category: Sheet1!$C$2:$C$15346
Name city: Sheet1!$N$2:$N$15346
Name customer_type: Sheet1!$K$2:$K$15346
Name delivery_date: Sheet1!$J$2:$J$15346
Name discount: Sheet1!$E$2:$E$15346
Name discount_value: Sheet1!$F$2:$F$1048576
Name NativeTimeline_order_date: #N/A
Name Net_Revenue: Sheet1!$G$2:$G$15346
Name order_date: Sheet1!$I$2:$I$15346
Name order_id: Sheet1!$A$2:$A$15346
Name payment_mode: Sheet1!$L$2:$L$15346
Name profit: Sheet1!$M$2:$M$15346
Name quantity: Sheet1!$H$2:$H$15346
Name region: Sheet1!$B$2:$B$15346
Name sales: Sheet1!$D$2:$D$15346
Name Slicer_category: #N/A
Name Slicer_customer_type: #N/A
Name Slicer_region: #N/A

Sheet kpi
A3: Count of order_id | B3: Sum of sales | C3: Sum of profit | D3: Sum of quantity
A4: 5745 | B4: 14821801 | C4: 2581023.9 | D4: 28599

Sheet Sheet1
A1: order_id | B1: region | C1: category | D1: sales | E1: discount | F1: discount value | G1: Net Revenue | H1: quantity | I1: order_date | J1: delivery_date | K1: customer_type | L1: payment_mode | M1: profit | N1: city
A2: ORD103171 | B2: East | C2: Grocery | D2: 109.39 | E2: 0.43 | F2: =D2*E2 -> 47.0377 | G2: =D2-F2 -> 62.3523 | H2: 9 | I2: 45240 | J2: 45246 | K2: New | L2: Cash | M2: 27.56 | N2: Delhi
A3: ORD113247 | B3: North | C3: Grocery | D3: 121.9 | E3: 0.04 | F3: =D3*E3 -> 4.876 | G3: =D3-F3 -> 117.024 | H3: 9 | I3: 45177 | J3: 45183 | K3: Member | L3: Card | M3: 9.99 | N3: Pune
A4: ORD102281 | B4: East | C4: Clothing | D4: 127.63 | E4: 0.04 | F4: =D4*E4 -> 5.1052 | G4: =D4-F4 -> 122.5248 | H4: 9 | I4: 45251 | J4: 45253 | K4: Regular | L4: Card | M4: 20.59 | N4: Mumbai | S4: total orders by region | V4: total sales by region
A5: ORD111856 | B5: East | C5: Home Care | D5: 129.11 | E5: 0.31 | F5: =D5*E5 -> 40.0241 | G5: =D5-F5 -> 89.0859 | H5: 9 | I5: 44987 | J5: 44991 | K5: Regular | L5: UPI | M5: 32.14 | N5: Mumbai | P5: Total Profit | S5: region | T5: no of ordes | V5: region | W5: sales
A6: ORD108687 | B6: East | C6: Electronics | D6: 145.93 | E6: 0.05 | F6: =D6*E6 -> 7.2965 | G6: =D6-F6 -> 138.6335 | H6: 9 | I6: 45279 | J6: 45280 | K6: New | L6: UPI | M6: 42.69 | N6: Chennai | P6: =SUM(profit) -> 6872139.8 | S6: north | T6: =COUNTIF(B:B,"North") -> 3924 | V6: North | W6: =SUMIF(B:B,"North",D:D) -> 10143913
A7: ORD105800 | B7: South | C7: Clothing | D7: 146.72 | E7: 0.05 | F7: =D7*E7 -> 7.336 | G7: =D7-F7 -> 139.384 | H7: 9 | I7: 45568 | J7: 45573 | K7: New | L7: Cash | M7: 36.52 | N7: Bangalore | S7: south | T7: =COUNTIF(B:B,"South") -> 3853 | V7: South | W7: =SUMIF(B:B,"South",D:D) -> 9851779.2
A8: ORD112039 | B8: West | C8: Personal Care | D8: 147.56 | E8: 0.05 | F8: =D8*E8 -> 7.378 | G8: =D8-F8 -> 140.182 | H8: 9 | I8: 45157 | J8: 45162 | K8: Member | L8: Card | M8: 15.01 | N8: Delhi | P8: Total Net Revenue | S8: east | T8: =COUNTIF(B:B,"East") -> 3778 | V8: East | W8: =SUMIF(B:B,"East",D:D) -> 9518321.9
A9: ORD113857 | B9: West | C9: Personal Care | D9: 147.69 | E9: 0.37 | F9: =D9*E9 -> 54.6453 | G9: =D9-F9 -> 93.0447 | H9: 9 | I9: 45616 | J9: 45621 | K9: Member | L9: Cash | M9: 32.48 | N9: Hyderabad | P9: =SUM(Net_Revenue) -> 29388623 | S9: west | T9: =COUNTIF(B:B,"West") -> 3790 | V9: west | W9: =SUMIF(B:B,"West",D:D) -> 9748863.1
A10: ORD111942 | B10: West | C10: Clothing | D10: 148.81 | E10: 0.25 | F10: =D10*E10 -> 37.2025 | G10: =D10-F10 -> 111.6075 | H10: 9 | I10: 45422 | J10: 45424 | K10: Member | L10: Card | M10: 12.14 | N10: Hyderabad | S10: Total | T10: =SUBTOTAL(109,Table2[no of ordes]) -> 15345 | V10: Total | W10: =SUBTOTAL(109,Table3[sales]) -> 39262878
A11: ORD104683 | B11: West | C11: Personal Care | D11: 149.6 | E11: 0.34 | F11: =D11*E11 -> 50.864 | G11: =D11-F11 -> 98.736 | H11: 9 | I11: 45565 | J11: 45568 | K11: Regular | L11: Card | M11: 38.61 | N11: Hyderabad | P11: Marketing Budget
A12: ORD111817 | B12: North | C12: Clothing | D12: 151.01 | E12: 0.49 | F12: =D12*E12 -> 73.9949 | G12: =D12-F12 -> 77.0151 | H12: 9 | I12: 45271 | J12: 45277 | K12: Member | L12: Cash | M12: 10.84 | N12: Hyderabad | P12: =P9*0.1 -> 2938862.3
A13: ORD108696 | B13: West | C13: Home Care | D13: 151.98 | E13: 0.45 | F13: =D13*E13 -> 68.391 | G13: =D13-F13 -> 83.589 | H13: 9 | I13: 45444 | J13: 45447 | K13: Member | L13: Card | M13: 41.21 | N13: Bangalore
A14: ORD111404 | B14: East | C14: Clothing | D14: 154.08 | E14: 0.28 | F14: =D14*E14 -> 43.1424 | G14: =D14-F14 -> 110.9376 | H14: 9 | I14: 45597 | J14: 45603 | K14: New | L14: UPI | M14: 9.95 | N14: Chennai
A15: ORD104897 | B15: North | C15: Grocery | D15: 158.62 | E15: 0.4 | F15: =D15*E15 -> 63.448 | G15: =D15-F15 -> 95.172 | H15: 9 | I15: 45646 | J15: 45651 | K15: Regular | L15: UPI | M15: 8.42 | N15: Hyderabad
A16: ORD104827 | B16: West | C16: Grocery | D16: 158.7 | E16: 0.37 | F16: =D16*E16 -> 58.719 | G16: =D16-F16 -> 99.981 | H16: 9 | I16: 44955 | J16: 44956 | K16: Member | L16: UPI | M16: 30.08 | N16: Chennai
A17: ORD101037 | B17: East | C17: Home Care | D17: 159.04 | E17: 0.14 | F17: =D17*E17 -> 22.2656 | G17: =D17-F17 -> 136.7744 | H17: 9 | I17: 45163 | J17: 45165 | K17: Member | L17: Card | M17: 16.77 | N17: Delhi
A18: ORD100890 | B18: East | C18: Clothing | D18: 159.35 | E18: 0.35 | F18: =D18*E18 -> 55.7725 | G18: =D18-F18 -> 103.5775 | H18: 9 | I18: 44987 | J18: 44994 | K18: Regular | L18: UPI | M18: 41.86 | N18: Pune
A19: ORD112235 | B19: West | C19: Electronics | D19: 161.57 | E19: 0.34 | F19: =D19*E19 -> 54.9338 | G19: =D19-F19 -> 106.6362 | H19: 9 | I19: 45629 | J19: 45633 | K19: Regular | L19: Card | M19: 25.22 | N19: Chennai | T19: =averageofclothing -> 0
A20: ORD112037 | B20: West | C20: Home Care | D20: 164.85 | E20: 0.21 | F20: =D20*E20 -> 34.6185 | G20: =D20-F20 -> 130.2315 | H20: 9 | I20: 45411 | J20: 45414 | K20: New | L20: Cash | M20: 43.54 | N20: Hyderabad
A21: ORD114075 | B21: West | C21: Clothing | D21: 167.03 | E21: 0.45 | F21: =D21*E21 -> 75.1635 | G21: =D21-F21 -> 91.8665 | H21: 9 | I21: 45602 | J21: 45603 | K21: Member | L21: UPI | M21: 34.76 | N21: Bangalore
A22: ORD110184 | B22: South | C22: Home Care | D22: 169.4 | E22: 0.41 | F22: =D22*E22 -> 69.454 | G22: =D22-F22 -> 99.946 | H22: 9 | I22: 45222 | J22: 45224 | K22: Member | L22: Card | M22: 27.65 | N22: Hyderabad
A23: ORD113016 | B23: East | C23: Home Care | D23: 172.2 | E23: 0.39 | F23: =D23*E23 -> 67.158 | G23: =D23-F23 -> 105.042 | H23: 9 | I23: 44939 | J23: 44940 | K23: New | L23: Card | M23: 18.62 | N23: Delhi
A24: ORD102430 | B24: West | C24: Personal Care | D24: 176.56 | E24: 0.45 | F24: =D24*E24 -> 79.452 | G24: =D24-F24 -> 97.108 | H24: 9 | I24: 45003 | J24: 45010 | K24: Regular | L24: Card | M24: 34.83 | N24: Pune
A25: ORD113451 | B25: South | C25: Home Care | D25: 184.7 | E25: 0.27 | F25: =D25*E25 -> 49.869 | G25: =D25-F25 -> 134.831 | H25: 9 | I25: 45196 | J25: 45199 | K25: Member | L25: UPI | M25: 26.94 | N25: Pune
A26: ORD107078 | B26: West | C26: Clothing | D26: 185.55 | E26: 0.01 | F26: =D26*E26 -> 1.8555 | G26: =D26-F26 -> 183.6945 | H26: 9 | I26: 45433 | J26: 45437 | K26: New | L26: UPI | M26: 45.1 | N26: Hyderabad
A27: ORD113378 | B27: West | C27: Personal Care | D27: 185.62 | E27: 0.16 | F27: =D27*E27 -> 29.6992 | G27: =D27-F27 -> 155.9208 | H27: 9 | I27: 45034 | J27: 45039 | K27: Regular | L27: Cash | M27: 23.12 | N27: Chennai
A28: ORD112172 | B28: West | C28: Personal Care | D28: 190.18 | E28: 0.42 | F28: =D28*E28 -> 79.8756 | G28: =D28-F28 -> 110.3044 | H28: 9 | I28: 44934 | J28: 44941 | K28: New | L28: Card | M28: 42.64 | N28: Pune
A29: ORD112532 | B29: South | C29: Home Care | D29: 190.2 | E29: 0.14 | F29: =D29*E29 -> 26.628 | G29: =D29-F29 -> 163.572 | H29: 9 | I29: 45045 | J29: 45050 | K29: Member | L29: Card | M29: 37.55 | N29: Mumbai
A30: ORD107885 | B30: South | C30: Electronics | D30: 191.28 | E30: 0.08 | F30: =D30*E30 -> 15.3024 | G30: =D30-F30 -> 175.9776 | H30: 9 | I30: 45651 | J30: 45658 | K30: New | L30: Card | M30: 20.84 | N30: Mumbai
A31: ORD114015 | B31: East | C31: Electronics | D31: 192.66 | E31: 0.23 | F31: =D31*E31 -> 44.3118 | G31: =D31-F31 -> 148.3482 | H31: 9 | I31: 45295 | J31: 45300 | K31: Regular | L31: UPI | M31: 54.73 | N31: Bangalore
... A15346: ORD111193 | B15346: South | C15346: Home Care | D15346: 4994.14 | E15346: 0.43 | F15346: =D15346*E15346 -> 2147.4802 | G15346: =D15346-F15346 -> 2846.6598 | H15346: 1 | I15346: 45573 | J15346: 45574 | K15346: Regular | L15346: Cash | M15346: 1177.17 | N15346: Bangalore

Sheet Sheet16
A1: Row Labels | B1: Count of order_id | E1: Row Labels | F1: Sum of sales
A2: North | B2: 1924 | E2: Personal Care | F2: 3036996.5 | I2: Row Labels | J2: Sum of Net Revenue | L2: Row Labels | M2: Sum of Net Revenue
A3: South | B3: 1933 | E3: Home Care | F3: 3032946.6 | I3: Delhi | J3: 1897526.3 | L3: Card | M3: 3879660.1
A4: West | B4: 1888 | E4: Clothing | F4: 2959534.4 | I4: Mumbai | J4: 1896622.3 | L4: Cash | M4: 3655405.8
A5: Grand Total | B5: 5745 | E5: Grocery | F5: 2937053.6 | I5: Bangalore | J5: 1895291.8 | L5: UPI | M5: 3585236.6
E6: Electronics | F6: 2855270.2 | I6: Chennai | J6: 1857899 | L6: Grand Total | M6: 11120303
E7: Grand Total | F7: 14821801 | I7: Hyderabad | J7: 1822841.7
I8: Pune | J8: 1750121.4
I9: Grand Total | J9: 11120303

Sheet DASHBOARD
A1: DmartSales Analysis Dashboard
D4: total orders | F4: total sale | H4: total profit | J4: total quantity
D5: =GETPIVOTDATA("Count of order_id",kpi!$A$3) -> 5745 | F5: =GETPIVOTDATA("Sum of sales",kpi!$A$3) -> 14821801 | H5: =GETPIVOTDATA("Sum of profit",kpi!$A$3) -> 2581023.9 | J5: =GETPIVOTDATA("Sum of quantity",kpi!$A$3) -> 28599

Sheet Sheet9
A1: ID | B1: NAME | C1: AGE
A2: 10 | B2: OM | C2: 18
A3: 20 | B3: ONKESH | C3: 20 | F3: =MATCH("ONKESH",B:B,) -> 3
A4: 30 | B4: AJIT | C4: 22

Sheet Sheet8
A1: 10
A2: 20
A3: abc
A4: 30 | C4: =COUNTBLANK(A1:A12) -> 1
A5: pqr | C5: =COUNT(A1:A12) -> 8
A6: 90 | C6: =COUNTA(A1:A12,COUNTBLANK(A1:A12)) -> 12 | E6: Bamboozeld | G6: =UPPER(E6) -> BAMBOOZELD | J6: onkesh | K6: dike | L6: =_xlfn.CONCAT(J6,K6) -> onkeshdike
A7: 30 | C7: =ROWS(A1:A12) -> 12 | G7: =LOWER(E6) -> bamboozeld | L7: =_xlfn.CONCAT(J6,"- ",K6) -> onkesh- dike | P7: Boat
A8: 40 | G8: =PROPER(E6) -> Bamboozeld | P8: World
P9: Cat
A10: 31 | P10: Bat
A11: pqr | E11: " Hello " | G11: =TRIM(E11) -> " Hello " | K11: onkesh@gmail.com | P11: Mat | Q11: =COUNTIF(P:P,"Ba*") -> 4
A12: 91 | P12: Hello | Q12: =COUNTIF(P:P,"?a*") -> 11
K13: =SUBSTITUTE(K11,"gmail","yahoo") -> onkesh@yahoo.com | N13: hello | O13: =FIND("l",N13) -> 3 | P13: Hat
G14: Bamboozeld | I14: =LEFT(G14,6) -> Bamboo | K14: =REPLACE(K13,8,5,"yahoo") -> onkesh@yahoo.com | O14: =SEARCH("E",N13) -> 2 | P14: Bot
I15: =LEFT(G14,2) -> Ba | P15: Ball
I16: =RIGHT(G14,5) -> ozeld | K16: hello | P16: Mall
I17: =MID(G14,1,10) -> Bamboozeld | P17: Make
I18: =MID(G14,1,5) -> Bambo | P18: Bake
P19: Ba* | Q19: =COUNTIF(P:P,"Ba~*") -> 1
P20: ?at | Q20: =COUNTIF(P:P,"~>at") -> 0
P21: ?a*

Sheet Sheet6
A1: age | B1: citizen | D1: status | E1: status
A2: 12 | B2: india | C2: status | D2: =IF(AND(A2>=18,B2="india"),"Eligible","ineligibal") -> ineligibal | E2: =IF(OR(A2>=18,B2="india"),"Eligiable","ineligible") -> Eligiable | J2: marks | K2: grade
A3: 24 | B3: us | C3: =IF(A2>=18,"eligibale","ineligibale") -> ineligibale | D3: =IF(AND(A3>=18,B3="india"),"Eligible","ineligibal") -> ineligibal | E3: =IF(OR(A3>=18,B3="india"),"Eligiable","ineligible") -> Eligiable | J3: 81 | K3: =IF(J3>80,"A",IF(J3>60,"B",IF(J3>40,"C","F"))) -> A
A4: 15 | B4: india | C4: =IF(A3>=18,"eligibale","ineligibale") -> eligibale | D4: =IF(AND(A4>=18,B4="india"),"Eligible","ineligibal") -> ineligibal | E4: =IF(OR(A4>=18,B4="india"),"Eligiable","ineligible") -> Eligiable | J4: 40 | K4: =IF(J4>80,"A",IF(J4>60,"B",IF(J4>40,"C","F"))) -> F
A5: 18 | B5: uk | C5: =IF(A4>=18,"eligibale","ineligibale") -> ineligibale | D5: =IF(AND(A5>=18,B5="india"),"Eligible","ineligibal") -> ineligibal | E5: =IF(OR(A5>=18,B5="india"),"Eligiable","ineligible") -> Eligiable | J5: 45 | K5: =IF(J5>80,"A",IF(J5>60,"B",IF(J5>40,"C","F"))) -> C
A6: 20 | B6: us | C6: =IF(A5>=18,"eligibale","ineligibale") -> eligibale | D6: =IF(AND(A6>=18,B6="india"),"Eligible","ineligibal") -> ineligibal | E6: =IF(OR(A6>=18,B6="india"),"Eligiable","ineligible") -> Eligiable | J6: 35 | K6: =IF(J6>80,"A",IF(J6>60,"B",IF(J6>40,"C","F"))) -> F
A7: 17 | B7: india | C7: =IF(A6>=18,"eligibale","ineligibale") -> eligibale | D7: =IF(AND(A7>=18,B7="india"),"Eligible","ineligibal") -> ineligibal | E7: =IF(OR(A7>=18,B7="india"),"Eligiable","ineligible") -> Eligiable | H7: =AND(10>20,20>10) -> FALSE | J7: 60 | K7: =IF(J7>80,"A",IF(J7>60,"B",IF(J7>40,"C","F"))) -> C
A8: 23 | B8: india | C8: =IF(A7>=18,"eligibale","ineligibale") -> ineligibale | D8: =IF(AND(A8>=18,B8="india"),"Eligible","ineligibal") -> Eligible | E8: =IF(OR(A8>=18,B8="india"),"Eligiable","ineligible") -> Eligiable | H8: =AND(10=10,20>10) -> TRUE | J8: 70 | K8: =IF(J8>80,"A",IF(J8>60,"B",IF(J8>40,"C","F"))) -> B
J9: 55 | K9: =IF(J9>80,"A",IF(J9>60,"B",IF(J9>40,"C","F"))) -> C

Sheet Sheet7

Sheet Sheet4
A1: Fruit | B1: Price | C1: City | I1: email | K1: .in
A2: Apple | B2: 50 | C2: Mumbai | H2: xyz | I2: xyz@domain.com | K2: =SUBSTITUTE(I2,".com",".in") -> xyz@domain.in | L2: 111222333 | M2: =REPLACE(L2,4,3,"***") -> 111***333
A3: Banana | B3: 100 | C3: Vashi | D3: Total Sum Of Apple | E3: Count Of Apple | F3: Average Price Of Apple | H3: abc | I3: abc@domain.com | K3: =SUBSTITUTE(I3,".com",".in") -> abc@domain.in | L3: 222333444 | M3: =REPLACE(L3,4,3,"***") -> 222***444
A4: Orange | B4: 150 | C4: Thane | D4: =SUMIF(A2:A13,"Apple",B2:B13) -> 2000 | E4: =COUNTIF(A2:A13,"Apple") -> 6 | H4: pqr | I4: pqr@domain.com | K4: =SUBSTITUTE(I4,".com",".in") -> pqr@domain.in
A5: Apple | B5: 200 | C5: Panvel | D5: Mumbai Avg | H5: mno | I5: mno@domain.com | K5: =SUBSTITUTE(I5,".com",".in") -> mno@domain.in
A6: kiwi | B6: 250 | C6: Mumbai | D6: =AVERAGEIFS(B2:B13,A2:A13,"Apple",C2:C13,"Mumbai") -> 383.33333 | H6: lst | I6: lst@domain.com | K6: =SUBSTITUTE(I6,".com",".in") -> lst@domain.in
A7: Apple | B7: 300 | C7: Vashi | H7: uvx | I7: uvx@domain.com | K7: =SUBSTITUTE(I7,".com",".in") -> uvx@domain.in
A8: Apple | B8: 350 | C8: Thane | H8: xyz | I8: xyz@domain.com | K8: =SUBSTITUTE(I8,".com",".in") -> xyz@domain.in
A9: Banana | B9: 400 | C9: Panvel | H9: abc | I9: abc@domain.com | K9: =SUBSTITUTE(I9,".com",".in") -> abc@domain.in
A10: Orange | B10: 450 | C10: Mumbai | H10: pqr | I10: pqr@domain.com | K10: =SUBSTITUTE(I10,".com",".in") -> pqr@domain.in
A11: Apple | B11: 500 | C11: Mumbai | H11: mno | I11: mno@domain.com | K11: =SUBSTITUTE(I11,".com",".in") -> mno@domain.in
A12: kiwi | B12: 550 | C12: Thane | H12: lst | I12: lst@domain.com | K12: =SUBSTITUTE(I12,".com",".in") -> lst@domain.in
A13: Apple | B13: 600 | C13: Mumbai | H13: uvx | I13: uvx@domain.com | K13: =SUBSTITUTE(I13,".com",".in") -> uvx@domain.in

Sheet Sheet2
A1: Roll no | B1: Name | C1: Marks
A2: 1 | B2: Rahul | C2: =VLOOKUP(A2,Sheet3!$A$1:$C$9,MATCH("Marks",Sheet3!$1:$1,0),FALSE) -> 65
A3: 2 | B3: Kunal | C3: =VLOOKUP(A3,Sheet3!$A$1:$C$9,MATCH("Marks",Sheet3!$1:$1,0),FALSE) -> 76
A4: 6 | B4: Hardik | C4: =VLOOKUP(A4,Sheet3!$A$1:$C$9,MATCH("Marks",Sheet3!$1:$1,0),FALSE) -> 77
A5: 4 | B5: Dhoni | C5: =VLOOKUP(A5,Sheet3!$A$1:$C$9,MATCH("Marks",Sheet3!$1:$1,0),FALSE) -> 34
A6: 5 | B6: Rohan | C6: =VLOOKUP(A6,Sheet3!$A$1:$C$9,MATCH("Marks",Sheet3!$1:$1,0),FALSE) -> 90
A7: 3 | B7: Kurnal | C7: =VLOOKUP(A7,Sheet3!$A$1:$C$9,MATCH("Marks",Sheet3!$1:$1,0),FALSE) -> 89
A8: 7 | B8: Pandya | C8: =VLOOKUP(A8,Sheet3!$A$1:$C$9,MATCH("Marks",Sheet3!$1:$1,0),FALSE) -> 56
A9: 8 | B9: Mahendra | C9: =VLOOKUP(A9,Sheet3!$A$1:$C$9,MATCH("Marks",Sheet3!$1:$1,0),FALSE) -> 87

Sheet Sheet5
A1: Rollno | B1: 1 | C1: 2 | D1: 3 | E1: 4 | F1: 5 | G1: 6 | H1: 7 | I1: 8 | J1: 9
A2: Name | B2: Rahul | C2: Kunal | D2: Hardik | E2: Dhoni | F2: Rahul | G2: Kunal | H2: Hardik | I2: Dhoni | J2: Rahul
A3: Marks | B3: 34 | C3: 45 | D3: 67 | E3: 89 | F3: 98 | G3: 87 | H3: 76 | I3: 65 | J3: 54
G10: =HLOOKUP(7,B1:J3,3,FALSE) -> 76

Sheet Sheet3
A1: Roll no | C1: Marks
A2: 1 | C2: 65
A3: 2 | C3: 76
A4: 3 | C4: 89
A5: 4 | C5: 34 | H5: 10 | I5: 4
A6: 5 | C6: 90 | H6: 20 | I6: 1
A7: 6 | C7: 77 | H7: 30 | I7: 0
A8: 7 | C8: 56 | H8: 40 | I8: 2
A9: 8 | C9: 87 | H9: 50 | I9: 6
E10: =MATCH("Marks",1:1,0) -> 3 | H10: 60 | I10: 8
C11: =SUBTOTAL(1,C2:C3) -> 70.5 | H11: 70 | I11: 9
C12: =SUBTOTAL(2,C2:C9) -> 8 | H12: 80 | I12: 3
