Workbook

Sheet Sales_Data
A1: NEXUS RETAIL — SALES TRANSACTION DATA (Master Dataset) | L1: 1.1 | M1: 1.18
A2: Order ID | B2: Salesperson | C2: Region | D2: Product | E2: Qty | F2: Unit Price (₹) | G2: Discount % | H2: Sale Date | I2: Month | J2: Total Sale (₹) | K2: Status | O2: sales person info
A3: ORD001 | B3: Priya Sharma | C3: North | D3: Laptop | E3: 3 | F3: 55000 | G3: 5 | H3: 2024-01-08 | I3: January | J3: =E3*F3*(1-G3/100) -> 156750 | K3: Low | L3: =Sales_Data!F3*1.1 -> 60500 | M3: =F3*$M$1 -> 64900 | N3: =IF(Sales_Data!J3>=100000,"Big Deal","Reguler") -> Big Deal | O3: =_xlfn.XLOOKUP(Sales_Data!B3,Salesperson_Info!$A$3:$A$7,Salesperson_Info!$D$3:$D$7,"not found") -> priya@nexus.com
A4: ORD002 | B4: Rahul Mehta | C4: South | D4: Mobile | E4: 7 | F4: 18000 | G4: 0 | H4: 2024-01-15 | I4: January | J4: =E4*F4*(1-G4/100) -> 126000 | K4: Medium | L4: =Sales_Data!F4*1.1 -> 19800 | M4: =F4*$M$1 -> 21240 | N4: =IF(Sales_Data!J4>=100000,"Big Deal","Reguler") -> Big Deal | O4: =_xlfn.XLOOKUP(Sales_Data!B4,Salesperson_Info!$A$3:$A$7,Salesperson_Info!$D$3:$D$7,"not found") -> rahul@nexus.com
A5: ORD003 | B5: Anita Desai | C5: East | D5: Tablet | E5: 4 | F5: 28000 | G5: 8 | H5: 2024-01-22 | I5: January | J5: =E5*F5*(1-G5/100) -> 103040 | K5: Low | L5: =Sales_Data!F5*1.1 -> 30800 | M5: =F5*$M$1 -> 33040 | N5: =IF(Sales_Data!J5>=100000,"Big Deal","Reguler") -> Big Deal | O5: =_xlfn.XLOOKUP(Sales_Data!B5,Salesperson_Info!$A$3:$A$7,Salesperson_Info!$D$3:$D$7,"not found") -> anita@nexus.com
A6: ORD004 | B6: Vikram Nair | C6: West | D6: Laptop | E6: 2 | F6: 55000 | G6: 10 | H6: 2024-02-03 | I6: February | J6: =E6*F6*(1-G6/100) -> 99000 | K6: Low | L6: =Sales_Data!F6*1.1 -> 60500 | M6: =F6*$M$1 -> 64900 | N6: =IF(Sales_Data!J6>=100000,"Big Deal","Reguler") -> Reguler | O6: =_xlfn.XLOOKUP(Sales_Data!B6,Salesperson_Info!$A$3:$A$7,Salesperson_Info!$D$3:$D$7,"not found") -> vikram@nexus.com
A7: ORD005 | B7: Sunita Rao | C7: North | D7: Headphones | E7: 12 | F7: 3500 | G7: 0 | H7: 2024-02-10 | I7: February | J7: =E7*F7*(1-G7/100) -> 42000 | K7: High | L7: =Sales_Data!F7*1.1 -> 3850 | M7: =F7*$M$1 -> 4130 | N7: =IF(Sales_Data!J7>=100000,"Big Deal","Reguler") -> Reguler | O7: =_xlfn.XLOOKUP(Sales_Data!B7,Salesperson_Info!$A$3:$A$7,Salesperson_Info!$D$3:$D$7,"not found") -> sunita@nexus.com
A8: ORD006 | B8: Priya Sharma | C8: South | D8: Monitor | E8: 5 | F8: 14000 | G8: 5 | H8: 2024-02-18 | I8: February | J8: =E8*F8*(1-G8/100) -> 66500 | K8: Medium | L8: =Sales_Data!F8*1.1 -> 15400 | M8: =F8*$M$1 -> 16520 | N8: =IF(Sales_Data!J8>=100000,"Big Deal","Reguler") -> Reguler | O8: =_xlfn.XLOOKUP(Sales_Data!B8,Salesperson_Info!$A$3:$A$7,Salesperson_Info!$D$3:$D$7,"not found") -> priya@nexus.com
A9: ORD007 | B9: Rahul Mehta | C9: East | D9: Laptop | E9: 1 | F9: 55000 | G9: 0 | H9: 2024-03-05 | I9: March | J9: =E9*F9*(1-G9/100) -> 55000 | K9: Low | L9: =Sales_Data!F9*1.1 -> 60500 | M9: =F9*$M$1 -> 64900 | N9: =IF(Sales_Data!J9>=100000,"Big Deal","Reguler") -> Reguler | O9: =_xlfn.XLOOKUP(Sales_Data!B9,Salesperson_Info!$A$3:$A$7,Salesperson_Info!$D$3:$D$7,"not found") -> rahul@nexus.com
A10: ORD008 | B10: Anita Desai | C10: West | D10: Mobile | E10: 9 | F10: 18000 | G10: 12 | H10: 2024-03-12 | I10: March | J10: =E10*F10*(1-G10/100) -> 142560 | K10: Medium | L10: =Sales_Data!F10*1.1 -> 19800 | M10: =F10*$M$1 -> 21240 | N10: =IF(Sales_Data!J10>=100000,"Big Deal","Reguler") -> Big Deal | O10: =_xlfn.XLOOKUP(Sales_Data!B10,Salesperson_Info!$A$3:$A$7,Salesperson_Info!$D$3:$D$7,"not found") -> anita@nexus.com
A11: ORD009 | B11: Vikram Nair | C11: North | D11: Tablet | E11: 6 | F11: 28000 | G11: 0 | H11: 2024-03-20 | I11: March | J11: =E11*F11*(1-G11/100) -> 168000 | K11: Medium | L11: =Sales_Data!F11*1.1 -> 30800 | M11: =F11*$M$1 -> 33040 | N11: =IF(Sales_Data!J11>=100000,"Big Deal","Reguler") -> Big Deal | O11: =_xlfn.XLOOKUP(Sales_Data!B11,Salesperson_Info!$A$3:$A$7,Salesperson_Info!$D$3:$D$7,"not found") -> vikram@nexus.com
A12: ORD010 | B12: Sunita Rao | C12: South | D12: Keyboard | E12: 20 | F12: 1200 | G12: 0 | H12: 2024-04-02 | I12: April | J12: =E12*F12*(1-G12/100) -> 24000 | K12: High | L12: =Sales_Data!F12*1.1 -> 1320 | M12: =F12*$M$1 -> 1416 | N12: =IF(Sales_Data!J12>=100000,"Big Deal","Reguler") -> Reguler | O12: =_xlfn.XLOOKUP(Sales_Data!B12,Salesperson_Info!$A$3:$A$7,Salesperson_Info!$D$3:$D$7,"not found") -> sunita@nexus.com
A13: ORD011 | B13: Priya Sharma | C13: East | D13: Laptop | E13: 4 | F13: 55000 | G13: 7 | H13: 2024-04-14 | I13: April | J13: =E13*F13*(1-G13/100) -> 204600 | K13: Low | L13: =Sales_Data!F13*1.1 -> 60500 | M13: =F13*$M$1 -> 64900 | N13: =IF(Sales_Data!J13>=100000,"Big Deal","Reguler") -> Big Deal | O13: =_xlfn.XLOOKUP(Sales_Data!B13,Salesperson_Info!$A$3:$A$7,Salesperson_Info!$D$3:$D$7,"not found") -> priya@nexus.com
A14: ORD012 | B14: Rahul Mehta | C14: West | D14: Monitor | E14: 3 | F14: 14000 | G14: 5 | H14: 2024-04-21 | I14: April | J14: =E14*F14*(1-G14/100) -> 39900 | K14: Low | L14: =Sales_Data!F14*1.1 -> 15400 | M14: =F14*$M$1 -> 16520 | N14: =IF(Sales_Data!J14>=100000,"Big Deal","Reguler") -> Reguler | O14: =_xlfn.XLOOKUP(Sales_Data!B14,Salesperson_Info!$A$3:$A$7,Salesperson_Info!$D$3:$D$7,"not found") -> rahul@nexus.com
... A27: ORD025 | B27: Sunita Rao | C27: North | D27: Mobile | E27: 11 | F27: 18000 | G27: 0 | H27: 2024-08-26 | I27: August | J27: =E27*F27*(1-G27/100) -> 198000 | K27: High | L27: =Sales_Data!F27*1.1 -> 19800 | M27: =F27*$M$1 -> 21240 | N27: =IF(Sales_Data!J27>=100000,"Big Deal","Reguler") -> Big Deal | O27: =_xlfn.XLOOKUP(Sales_Data!B27,Salesperson_Info!$A$3:$A$7,Salesperson_Info!$D$3:$D$7,"not found") -> sunita@nexus.com

Sheet Product_Master
A1: PRODUCT MASTER TABLE (use for VLOOKUP / XLOOKUP tasks)
A2: Product | B2: Category | C2: MRP (₹) | D2: Cost Price (₹) | E2: Gross Margin %
A3: Laptop | B3: Electronics | C3: 55000 | D3: 32000 | E3: =((C3-D3)/C3)*100 -> 41.818182
A4: Mobile | B4: Electronics | C4: 18000 | D4: 10500 | E4: =((C4-D4)/C4)*100 -> 41.666667
A5: Tablet | B5: Electronics | C5: 28000 | D5: 17000 | E5: =((C5-D5)/C5)*100 -> 39.285714
A6: Monitor | B6: Electronics | C6: 14000 | D6: 8200 | E6: =((C6-D6)/C6)*100 -> 41.428571
A7: Headphones | B7: Accessories | C7: 3500 | D7: 1800 | E7: =((C7-D7)/C7)*100 -> 48.571429
A8: Keyboard | B8: Accessories | C8: 1200 | D8: 600 | E8: =((C8-D8)/C8)*100 -> 50

Sheet Salesperson_Info
A1: SALESPERSON REFERENCE TABLE (use for VLOOKUP / HLOOKUP tasks)
A2: Salesperson | B2: Region | C2: Target (₹) | D2: Email | E2: Joined Year
A3: Priya Sharma | B3: North | C3: 600000 | D3: priya@nexus.com | E3: 2019
A4: Rahul Mehta | B4: South | C4: 550000 | D4: rahul@nexus.com | E4: 2020
A5: Anita Desai | B5: East | C5: 500000 | D5: anita@nexus.com | E5: 2018
A6: Vikram Nair | B6: West | C6: 580000 | D6: vikram@nexus.com | E6: 2021
A7: Sunita Rao | B7: North | C7: 620000 | D7: sunita@nexus.com | E7: 2017

Sheet Monthly_Targets
A1: MONTHLY TARGETS & ACTUALS (use for HLOOKUP task)
A2: Metric | B2: Jan | C2: Feb | D2: Mar | E2: Apr | F2: May | G2: Jun | H2: Jul | I2: Aug
A3: Sales Target (₹) | B3: 500000 | C3: 480000 | D3: 520000 | E3: 490000 | F3: 510000 | G3: 530000 | H3: 515000 | I3: 525000
A4: Actual Sales (₹) | B4: 462000 | C4: 503000 | D4: 487000 | E4: 512000 | F4: 478000 | G4: 541000 | H4: 496000 | I4: 533000
A5: No. of Orders | B5: 8 | C5: 9 | D5: 7 | E5: 8 | F5: 7 | G5: 9 | H5: 8 | I5: 9

Sheet Assignment
A1: NEXUS RETAIL — ADVANCED EXCEL ASSIGNMENT
A2: Dataset: Sales_Data | Product_Master | Salesperson_Info | Monthly_Targets · All answers go in Column E
B4: Student Name:
B5: Date:
B6: Batch:
A8: # | B8: Topic | C8: Task / Question | D8: Your Answer / Formula | E8: Marks
A9: MODULE 1 BASIC FORMULAS — SUM, AVERAGE, COUNT, MIN, MAX
A10: # | B10: Topic | C10: Task / Question | D10: Your Answer / Formula | E10: Marks
A11: 1 | B11: SUM | C11: Calculate the total revenue from ALL 25 orders in Sales_Data. | D11: =SUM(Sales_Data!J3:J27) -> 2582860
A12: 2 | B12: AVERAGE | C12: Find the average Unit Price across all 25 products sold. | D12: =AVERAGE(Sales_Data!F8:F27) -> 24180
A13: 3 | B13: COUNT | C13: Count how many orders have a Discount % greater than 0. | D13: =COUNTIF(Sales_Data!G3:G27,">0") -> 12
A14: 4 | B14: MIN/MAX | C14: Find the highest and lowest single Total Sale values. | D14: =MAX(Sales_Data!J3:J27)&"/"&MIN(Sales_Data!J3:J27) -> 204600/24000
A15: 5 | B15: COUNTA | C15: Count how many unique salesperson names appear in column B of Sales_Data (hint: use COUNTA on B3:B27). | D15: =COUNTA(_xlfn.UNIQUE(Sales_Data!B3:B27)) -> 5
A17: MODULE 2 CELL REFERENCES — RELATIVE, ABSOLUTE & MIXED
A18: # | B18: Topic | C18: Task / Question | D18: Your Answer / Formula | E18: Marks
A19: 1 | B19: Relative ref | C19: In a new column (col L) of Sales_Data, calculate a 'Revised Price' as Unit Price × 1.1 using a relative reference. Write the formula for row 3. | D19: "=F3*1.1"
A20: 2 | B20: Absolute ref | C20: In a new column (col M), calculate 'Price after Tax' as Unit Price × a GST rate of 18%. Put 1.18 in cell M1 and use an absolute reference to M1 in your formula. | D20: "=F3*$M$1"
A21: 3 | B21: Mixed ref | C21: Build a multiplication table in a blank area. Row holds values 1–5, column holds values 1–5. Write the formula for B2 that you can drag both right and down.
A22: 4 | B22: F4 trick | C22: Write a VLOOKUP formula in any blank cell that locks the table range using F4. Show the formula with $ signs applied to the range.
A24: MODULE 3 IF, AND, OR, NESTED IF — LOGICAL FUNCTIONS
A25: # | B25: Topic | C25: Task / Question | D25: Your Answer / Formula | E25: Marks
A26: 1 | B26: IF basic | C26: In Sales_Data column N, write a formula: if Total Sale ≥ 1,00,000 show 'Big Deal' else 'Regular'. Write the formula for row 3. | D26: "=IF(J3>=100000,"Big Deaal","Reguler")"
A27: 2 | B27: Nested IF | C27: In column O, classify orders: if Total Sale ≥ 2,00,000 → 'Platinum', ≥ 1,00,000 → 'Gold', ≥ 50,000 → 'Silver', else 'Bronze'.
A28: 3 | B28: IF + AND | C28: In column P, show 'Top Performer' if Region is 'North' AND Qty > 10, else blank.
A29: 4 | B29: IF + OR | C29: In column Q, flag 'Review' if the product is 'Laptop' OR the discount is > 8%.
A30: 5 | B30: IFS function | C30: Rewrite the Nested IF from Q2 using the IFS() function instead.
A32: MODULE 4 VLOOKUP & HLOOKUP — LOOKUP FUNCTIONS
A33: # | B33: Topic | C33: Task / Question | D33: Your Answer / Formula | E33: Marks
A34: 1 | B34: VLOOKUP basic | C34: Using Product_Master, write a VLOOKUP in a blank cell to find the Category for the product 'Tablet'.
A35: 2 | B35: VLOOKUP dynamic | C35: In a new column (col R) in Sales_Data, use VLOOKUP to pull the Cost Price for each product from Product_Master.
A36: 3 | B36: VLOOKUP + IFERROR | C36: Wrap the above formula in IFERROR to display 'Unknown' if the product is not found.
A37: 4 | B37: VLOOKUP cross-sheet | C37: Using Salesperson_Info, write a VLOOKUP to find the Sales Target for 'Anita Desai'.
A38: 5 | B38: HLOOKUP | C38: From Monthly_Targets, use HLOOKUP to find the Actual Sales for 'Jun'. | D38: =HLOOKUP("jun",Monthly_Targets!A2:I5,3,FALSE) -> 541000
A39: 6 | B39: HLOOKUP row 2 | C39: Use HLOOKUP to find the Sales Target for 'Apr' from Monthly_Targets. | D39: =HLOOKUP("APR",Monthly_Targets!A2:I5,3,FALSE) -> 512000
A40: 7 | B40: VLOOKUP limitation | C40: Explain in your own words why VLOOKUP cannot return the Salesperson name when you only know their email address. What would you use instead?
A42: MODULE 5 INDEX & MATCH — ADVANCED LOOKUP
A43: # | B43: Topic | C43: Task / Question | D43: Your Answer / Formula | E43: Marks
A44: 1 | B44: MATCH basic | C44: Find the row position of 'Vikram Nair' in Salesperson_Info column A using MATCH.
A45: 2 | B45: INDEX basic | C45: Use INDEX to return the value in row 2, column 3 of the Product_Master data range (A3:E8).
A46: 3 | B46: INDEX+MATCH | C46: Use INDEX+MATCH to find the Email of 'Sunita Rao' from Salesperson_Info. (This is what VLOOKUP cannot do when the return column is to the LEFT of your lookup column.)
A47: 4 | B47: Left lookup | C47: From Product_Master, find the Product name whose Cost Price is ₹10,500. Use INDEX+MATCH (VLOOKUP cannot do this).
A48: 5 | B48: Two-way lookup | C48: Use INDEX+MATCH+MATCH to find the value at the intersection of row 'Actual Sales (₹)' and column 'Mar' in Monthly_Targets.
A50: MODULE 6 SUMIF, COUNTIF, AVERAGEIF — CONDITIONAL AGGREGATION
A51: # | B51: Topic | C51: Task / Question | D51: Your Answer / Formula | E51: Marks
A52: 1 | B52: SUMIF | C52: Calculate total revenue from the 'North' region.
A53: 2 | B53: SUMIF product | C53: Calculate total revenue from Laptop sales only.
A54: 3 | B54: COUNTIF | C54: Count how many orders were placed in the 'South' region.
A55: 4 | B55: COUNTIF > | C55: Count orders where Qty is greater than 8.
A56: 5 | B56: AVERAGEIF | C56: Find the average Total Sale for orders in the 'East' region.
A57: 6 | B57: SUMIFS | C57: Calculate total revenue for 'Priya Sharma' in the 'North' region.
A58: 7 | B58: COUNTIFS | C58: Count orders where Product is 'Laptop' AND Discount > 0.
A59: 8 | B59: SUMPRODUCT | C59: Use SUMPRODUCT to find total revenue where Region='West' AND Qty>5.
A61: MODULE 7 TEXT FUNCTIONS — DATA CLEANING
A62: # | B62: Topic | C62: Task / Question | D62: Your Answer / Formula | E62: Marks
A63: 1 | B63: LEFT/RIGHT | C63: From 'ORD001' in Sales_Data A3, extract only the numeric part '001' using RIGHT.
A64: 2 | B64: MID | C64: From the email 'priya@nexus.com' in Salesperson_Info D3, extract the domain 'nexus.com' using MID and FIND.
A65: 3 | B65: CONCATENATE | C65: Combine Salesperson name and Region (from Salesperson_Info) as 'Priya Sharma — North'.
A66: 4 | B66: UPPER/LOWER | C66: Write formulas to display the product name 'Laptop' in ALL CAPS and all lowercase.
A67: 5 | B67: TRIM | C67: The name ' Rahul Mehta ' has extra spaces. Write TRIM to clean it.
A68: 6 | B68: LEN | C68: Count how many characters are in the Order ID 'ORD001'.
A69: 7 | B69: TEXT | C69: Format the number 165000 as currency with commas: ₹1,65,000. Use TEXT function.
A70: 8 | B70: SUBSTITUTE | C70: Replace 'nexus.com' with 'nexusretail.in' in Sunita Rao's email address.
A72: MODULE 8 DATE & TIME FUNCTIONS
A73: # | B73: Topic | C73: Task / Question | D73: Your Answer / Formula | E73: Marks
A74: 1 | B74: TODAY/NOW | C74: Write a formula that shows today's date and current date-time.
A75: 2 | B75: YEAR/MONTH | C75: From the Sale Date '2024-01-08' in Sales_Data H3, extract the Year and Month number.
A76: 3 | B76: DAY/WEEKDAY | C76: Extract the day number and the weekday name (e.g., 'Monday') from H3.
A77: 4 | B77: DATEDIF | C77: Calculate how many days have passed between the first order date (2024-01-08) and the last (2024-08-26).
A78: 5 | B78: EDATE | C78: An employee joined on 2019-03-15. What date is exactly 5 years later? Use EDATE.
A79: 6 | B79: NETWORKDAYS | C79: How many working days are between Jan 1 2024 and Mar 31 2024 (excluding weekends)?
A81: MODULE 9 CONDITIONAL FORMATTING — VISUAL ANALYSIS
A82: # | B82: Topic | C82: Task / Question | D82: Your Answer / Formula | E82: Marks
A83: 1 | B83: Highlight rule | C83: In Sales_Data, apply conditional formatting to column J (Total Sale) to highlight all cells > ₹1,00,000 in green fill.
A84: 2 | B84: Color scale | C84: Apply a 3-color scale (red-yellow-green) to the Qty column (E3:E27) so high qty shows green and low shows red.
A85: 3 | B85: Icon set | C85: Apply the 3-arrow icon set to the Discount % column (G3:G27).
A86: 4 | B86: Formula rule | C86: Highlight entire rows in Sales_Data where the product is 'Laptop' using a formula-based rule.
A87: 5 | B87: Duplicate values | C87: Highlight duplicate Order IDs in column A using the built-in Duplicate Values rule.
A88: 6 | B88: Data bars | C88: Apply data bars to the Total Sale column (J3:J27) to visually compare order sizes.
A90: MODULE 10 DATA VALIDATION & NAMED RANGES
A91: # | B91: Topic | C91: Task / Question | D91: Your Answer / Formula | E91: Marks
A92: 1 | B92: Dropdown list | C92: In a new sheet or blank area, create a dropdown in a cell allowing only these regions: North, South, East, West.
A93: 2 | B93: Whole number | C93: Create a validation rule that only allows Qty values between 1 and 100.
A94: 3 | B94: Custom formula | C94: Create a validation that rejects any discount > 20% using a custom formula.
A95: 4 | B95: Named range | C95: Create a named range called 'SalesData' for the range Sales_Data!A2:J27. Then use it in a SUMIF.
A96: 5 | B96: Named range formula | C96: After creating the named range, write a SUMIF using the name instead of the raw range.
A98: MODULE 11 PIVOT TABLES — DATA SUMMARISATION
A99: # | B99: Topic | C99: Task / Question | D99: Your Answer / Formula | E99: Marks
A100: 1 | B100: Basic pivot | C100: Create a Pivot Table from Sales_Data showing total revenue (Sum of Total Sale) by Region. Insert in a new sheet.
A101: 2 | B101: Two-way pivot | C101: Create a Pivot Table showing total revenue by Region (rows) × Product (columns).
A102: 3 | B102: Salesperson pivot | C102: Create a Pivot Table showing each Salesperson's total revenue and order count.
A103: 4 | B103: Month pivot | C103: Create a Pivot Table showing total revenue by Month.
A104: 5 | B104: Slicer | C104: Add a Slicer for 'Region' to your first pivot table and filter to show only North and South.
A105: 6 | B105: Calculated field | C105: Add a calculated field 'Profit Est.' = Total Sale × 0.22 to any pivot table.
A106: 7 | B106: Pivot chart | C106: Create a bar chart from the Region × Revenue pivot table.
A108: MODULE 12 CHARTS & DATA VISUALISATION
A109: # | B109: Topic | C109: Task / Question | D109: Your Answer / Formula | E109: Marks
A110: 1 | B110: Bar chart | C110: Create a bar chart showing Total Sale per Salesperson using Sales_Data.
A111: 2 | B111: Line chart | C111: Using Monthly_Targets data, create a line chart comparing Sales Target vs Actual Sales across all 8 months.
A112: 3 | B112: Pie chart | C112: Create a pie chart showing the share of total orders by Region.
A113: 4 | B113: Combo chart | C113: Create a combo chart with Actual Sales as bars and Sales Target as a line on the same chart.
...
